<?xml version="1.0" encoding="utf8"?>
<entry><title>Lead developer (Python/Django) - CDI</title><link href="https://www.afpy.org/jobs/cortox-gb-lead-developer-110728" rel="alternate"></link><published>2011-07-28T19:13:24+02:00</published><updated>2013-03-31T22:50:20+02:00</updated><author><name>admin</name><email>florian.nicourt@greenbureau.fr</email></author><id>https://www.afpy.org/jobs/cortox-gb-lead-developer-110728</id><summary type="html">Nous sommes une jeune startup innovante avec une équipe expérimentée, qui a déjà trouvé un incubateur (Télécom ParisTech), des investisseurs et deux clients importants.

Nous recherchons un(e) lead developer passionné(e) par les technologies web et open source, qui aime travailler en équipe et a déjà conçu des sites web complexes avec de fortes contraintes de performance. </summary><content type="html">&lt;p&gt;Rôle
&lt;br /&gt;
&lt;br /&gt;- Etre force de proposition pour la conception de l’application : choix des technologies, architecture, modèle de données, systèmes de stockage, stratégie de sécurité, etc.
&lt;br /&gt;- Réaliser vous-même une partie des développements
&lt;br /&gt;- Recruter, piloter et encadrer une petite équipe de développement
&lt;br /&gt;- Coordonner et industrialiser les processus de développement
&lt;br /&gt;
&lt;br /&gt;Compétences
&lt;br /&gt;
&lt;br /&gt;- Au moins 5 ans d’expérience en développement web (Python, Apache/Lighttpd, Django, XHTML, CSS, JQuery, MySQL/PostgreSQL, etc.)
&lt;br /&gt;- Expert(e) en Python (Django de préférence)
&lt;br /&gt;- Maîtrise des problématiques de performance et fortes charges
&lt;br /&gt;- Familiarité avec les plateformes Linux&lt;/p&gt;</content><company>Greenbureau</company><address>Paris</address><contact>Florian</contact><location></location><phone>+33 6 28 09 85 09</phone><link href="http://www.greenbureau.fr" rel="about"></link></entry>