<?xml version="1.0" encoding="utf8"?>
<entry><title>Teaching &amp; Research Coding CDI at EM Lyon Business School</title><link href="https://www.afpy.org/jobs/teaching-research-coding-cdi-at-em-lyon-business-school-1" rel="alternate"></link><published>2017-10-24T15:20:54+02:00</published><updated>2017-10-24T15:24:37+02:00</updated><author><name>arnicas</name><email>cherny@em-lyon.com</email></author><id>https://www.afpy.org/jobs/teaching-research-coding-cdi-at-em-lyon-business-school-1</id><summary type="html">Seeking strong teachers to build and deliver programming and data analysis curriculum for non-engineers.</summary><content type="html">&lt;p&gt;EM-Lyon is building new courses in introductory programming and data analytics.  We need talented teachers who are motivated and skilled at teaching non-engineers to code.  We also need research coding support.  We are hiring for multiple positions at multiple levels.  If you know &lt;strong&gt;how to teach Python&lt;/strong&gt;, and have some &lt;strong&gt;data analytics experience&lt;/strong&gt; (e.g. advanced Excel, SQL, possibly Tableau or Qlik and pandas), you would be a great fit for us.  If you have some of this but not all of it, but are talented at teaching and organizing, get in touch!  More advanced data analysis skills like machine learning, neural nets, and data visualization would also be very welcome.&lt;/p&gt;
&lt;p&gt;For one version of the job ad, see the &lt;a class="external-link" href="http://data.em-lyon.com/2017/09/15/em-lyon-seeking-research-programmer-data-science-teacher-full-time/" target="_self" title=""&gt;Data R&amp;amp;D Institute post here&lt;/a&gt;.  A full portfolio including teaching references is not needed for first conversations with us. &lt;/p&gt;
&lt;p&gt;Please contact Lynn Cherny, cherny@em-lyon.com, for more info and to start a chat with us.&lt;/p&gt;
&lt;p&gt; &lt;/p&gt;</content><company>EM Lyon Business School</company><address>23 ave Guy de Collongue
emlyon business school
69130 Ecully</address><contact>Lynn Cherny</contact><location>Lyon, France</location><phone></phone><link href="http://www.em-lyon.com/fr/" rel="about"></link><link href="http://data.em-lyon.com/2017/09/15/em-lyon-seeking-research-programmer-data-science-teacher-full-time/" rel="via"></link></entry>